raspberrypi_control/__init__.py
raspberrypi_control/raspberrypi.py
raspberrypi_control-2.0.6.dist-info/licenses/LICENSE
raspberrypi_control-2.0.6.dist-info/METADATA
raspberrypi_control-2.0.6.dist-info/WHEEL
raspberrypi_control-2.0.6.dist-info/top_level.txt
raspberrypi_control-2.0.6.dist-info/RECORD
