Metadata-Version: 2.4
Name: raspberrypi_control
Version: 2.0.6
Summary: Control Raspberrypi board with ssh and python
Author-email: Geoloup Team <franckiebbb@gmail.com>
Project-URL: Homepage, https://github.com/Geoloup/raspberry_control/
Project-URL: Bug Tracker, https://github.com/Geoloup/raspberry_control/issues
Classifier: Programming Language :: Python :: 3
Classifier: License :: OSI Approved :: MIT License
Classifier: Operating System :: OS Independent
Requires-Python: >=3.10
License-File: LICENSE
Requires-Dist: requests
Requires-Dist: paramiko
Requires-Dist: psutil
Dynamic: license-file
